trafficLight.v
module trafficLight(
	input wire clk,
	input wire rst,
	input wire vech1,
	input wire vech2,
	output reg [2:0] light1,
	output reg [2:0] light2);

	localparam g1r2 = 2'b00;
	localparam y1r2 = 2'b01;
	localparam r1g2 = 2'b10;
	localparam r1y2 = 2'b11;
	
	reg [3:0] count;
	localparam timer =4'b0101; 
	localparam delay =4'b0001;
	
	reg [1:0] current, next;

	localparam green = 3'b100;
	localparam yellow = 3'b010;
	localparam red = 3'b001;

	always @(posedge clk) begin
		if (rst==1) begin
			current<=g1r2;			
			count<=4'b0000;
		end else begin
			current<=next;
			if (current!=next) begin
				count<=4'b0000;
			end else begin
				count<= count+1;
			end
		end	
	end
	always @(*) begin
		next = current;
		case (current)
			g1r2:begin
				if (vech1==0 && vech2==1) begin
					next=y1r2;
				end else if (vech1==1 && vech2==0) begin
					next=g1r2;
				end else if (vech1==1 && vech2==1) begin
					if (count>=timer) begin
						next=y1r2;
					end else begin
						next=g1r2;
					end	
				end else begin
					next=g1r2;
				end
			end
			y1r2:begin
				if (count>=delay) begin
					next=r1g2;
				end else begin
					next=y1r2;
				end
			end
                        r1g2:begin
                                if (vech1==0 && vech2==1) begin
                                        next=r1g2;
                                end else if (vech1==1 && vech2==0) begin
                                        next=r1y2;
                                end else if (vech1==1 && vech2==1) begin
                                        if (count>=timer) begin
                                                next=r1y2;
                                        end else begin
                                                next=r1g2;
                                        end
                                end else begin
                                        next=r1g2;
                                end
                        end
		
			r1y2:begin
                                if (count>=delay) begin
                                        next=g1r2;
                                end else begin
                                        next=r1y2;
                                end
                        end
			default:begin
				light1=green;
				light2=green;
			end
		endcase
	end
	always @(*) begin
		light1 = green;
		light2 = green;
		if (rst == 1) begin
                        light1 = green;
                        light2 = green;
                end else begin
			case (current)
				g1r2:begin
					light1=green;
					light2=red;
				end
				y1r2:begin
					light1=yellow;
					light2=red;
				end
				r1g2:begin
					light1=red;
					light2=green;
				end
				r1y2:begin
					light1=red;
					light2=green;
				end
			endcase
		end	
	end
endmodule

tb_trafficLight.v
module tb_trafficLight();
	reg clk,rst,vech1,vech2;
	wire [2:0] light1,light2;
	initial begin
		clk = 1'b1;
	end
	always #5 clk =~clk;
	trafficLight dut (.clk(clk),.rst(rst),.vech1(vech1),.vech2(vech2),.light1(light1),.light2(light2));
	initial begin
		$dumpfile("trafficLight.vcd");
		$dumpvars(0,tb_trafficLight);
		rst = 1; vech1=0;vech2=0;#10;
		rst=0;#10;
		vech1=0;vech2=1;#50;
		vech1=1;vech2=0;#50;
		vech1=1;vech2=1;#100;
		vech1=0;vech2=0;#30;
		rst=1;#10
		$finish;
	end
endmodule

trafficLight.vcd
$date
	Wed Jun 24 12:29:30 2026
$end
$version
	Icarus Verilog
$end
$timescale
	1s
$end
$scope module tb_trafficLight $end
$var wire 3 ! light2 [2:0] $end
$var wire 3 " light1 [2:0] $end
$var reg 1 # clk $end
$var reg 1 $ rst $end
$var reg 1 % vech1 $end
$var reg 1 & vech2 $end
$scope module dut $end
$var wire 1 # clk $end
$var wire 1 $ rst $end
$var wire 1 % vech1 $end
$var wire 1 & vech2 $end
$var reg 4 ' count [3:0] $end
$var reg 2 ( current [1:0] $end
$var reg 3 ) light1 [2:0] $end
$var reg 3 * light2 [2:0] $end
$var reg 2 + next [1:0] $end
$upscope $end
$upscope $end
$enddefinitions $end
#0
$dumpvars
b0 +
b100 *
b100 )
b0 (
b0 '
0&
0%
1$
1#
b100 "
b100 !
$end
#5
0#
#10
b1 '
b1 !
b1 *
1#
0$
#15
0#
#20
b10 "
b10 )
b1 !
b1 *
b0 '
b1 (
b1 +
1#
1&
#25
0#
#30
b10 +
b1 '
1#
#35
0#
#40
b100 !
b100 *
b1 "
b1 )
b0 '
b10 (
1#
#45
0#
#50
b1 '
1#
#55
0#
#60
b10 '
1#
#65
0#
#70
b1 "
b1 )
b0 '
b11 (
b11 +
1#
0&
1%
#75
0#
#80
b0 +
b1 '
1#
#85
0#
#90
b1 !
b1 *
b100 "
b100 )
b0 '
b0 (
1#
#95
0#
#100
b1 '
1#
#105
0#
#110
b10 '
1#
#115
0#
#120
b11 '
1#
1&
#125
0#
#130
b100 '
1#
#135
0#
#140
b1 +
b101 '
1#
#145
0#
#150
b10 "
b10 )
b1 !
b1 *
b0 '
b1 (
1#
#155
0#
#160
b10 +
b1 '
1#
#165
0#
#170
b100 !
b100 *
b1 "
b1 )
b0 '
b10 (
1#
#175
0#
#180
b1 '
1#
#185
0#
#190
b10 '
1#
#195
0#
#200
b11 '
1#
#205
0#
#210
b100 '
1#
#215
0#
#220
b101 '
1#
0&
0%
#225
0#
#230
b110 '
1#
#235
0#
#240
b111 '
1#
#245
0#
#250
b0 +
b0 '
b0 (
b100 "
b100 )
1#
1$
